langchain_primordia/__init__.py
langchain_primordia/callback.py
langchain_primordia-0.1.1.dist-info/METADATA
langchain_primordia-0.1.1.dist-info/WHEEL
langchain_primordia-0.1.1.dist-info/RECORD
