Metadata-Version: 2.4
Name: langchain-primordia
Version: 0.1.1
Summary: Primordia economic metering for LangChain - track AI costs with machine-readable receipts
Project-URL: Homepage, https://primordia.dev
Project-URL: Documentation, https://primordia.dev/docs/langchain
Project-URL: Repository, https://github.com/primordia-ai/langchain-primordia
Project-URL: Kernel, https://clearing.kaledge.app
Author-email: Primordia <dev@primordia.dev>
License-Expression: MIT
Keywords: agents,ai,costs,langchain,metering,settlement
Classifier: Development Status :: 4 - Beta
Classifier: Intended Audience :: Developers
Classifier: License :: OSI Approved :: MIT License
Classifier: Programming Language :: Python :: 3
Classifier: Programming Language :: Python :: 3.9
Classifier: Programming Language :: Python :: 3.10
Classifier: Programming Language :: Python :: 3.11
Classifier: Programming Language :: Python :: 3.12
Classifier: Topic :: Software Development :: Libraries :: Python Modules
Requires-Python: >=3.9
Requires-Dist: langchain-core>=0.1.0
Provides-Extra: submit
Requires-Dist: requests>=2.28.0; extra == 'submit'
